com_vitalai_domain_social/__init__.py
com_vitalai_domain_social/domain-ontology/vital-social-0.2.304.owl
com_vitalai_domain_social/model/CampaignAction.py
com_vitalai_domain_social/model/CampaignAction.pyi
com_vitalai_domain_social/model/DirectMessage.py
com_vitalai_domain_social/model/DirectMessage.pyi
com_vitalai_domain_social/model/DomainOntology.py
com_vitalai_domain_social/model/Edge_hasCampaignAction.py
com_vitalai_domain_social/model/Edge_hasCampaignAction.pyi
com_vitalai_domain_social/model/Edge_hasCampaignActionDocument.py
com_vitalai_domain_social/model/Edge_hasCampaignActionDocument.pyi
com_vitalai_domain_social/model/Edge_hasCampaignActionFilterElement.py
com_vitalai_domain_social/model/Edge_hasCampaignActionFilterElement.pyi
com_vitalai_domain_social/model/Edge_hasContextAccount.py
com_vitalai_domain_social/model/Edge_hasContextAccount.pyi
com_vitalai_domain_social/model/Edge_hasFanCountry.py
com_vitalai_domain_social/model/Edge_hasFanCountry.pyi
com_vitalai_domain_social/model/Edge_hasFilter.py
com_vitalai_domain_social/model/Edge_hasFilter.pyi
com_vitalai_domain_social/model/Edge_hasFilterElement.py
com_vitalai_domain_social/model/Edge_hasFilterElement.pyi
com_vitalai_domain_social/model/Edge_hasSocialLocation.py
com_vitalai_domain_social/model/Edge_hasSocialLocation.pyi
com_vitalai_domain_social/model/Edge_hasSocialMediaAccount.py
com_vitalai_domain_social/model/Edge_hasSocialMediaAccount.pyi
com_vitalai_domain_social/model/Edge_hasSocialMediaCampaign.py
com_vitalai_domain_social/model/Edge_hasSocialMediaCampaign.pyi
com_vitalai_domain_social/model/Edge_hasTwitterAccount.py
com_vitalai_domain_social/model/Edge_hasTwitterAccount.pyi
com_vitalai_domain_social/model/Edge_hasTwitterApp.py
com_vitalai_domain_social/model/Edge_hasTwitterApp.pyi
com_vitalai_domain_social/model/FacebookAccount.py
com_vitalai_domain_social/model/FacebookAccount.pyi
com_vitalai_domain_social/model/FanCountry.py
com_vitalai_domain_social/model/FanCountry.pyi
vital_ai_social-0.1.5.dist-info/METADATA
vital_ai_social-0.1.5.dist-info/WHEEL
vital_ai_social-0.1.5.dist-info/entry_points.txt
vital_ai_social-0.1.5.dist-info/top_level.txt
vital_ai_social-0.1.5.dist-info/RECORD
